webhooks_bridge/__init__.py
webhooks_bridge/main.py
webhooks_bridge-0.1.1.dist-info/METADATA
webhooks_bridge-0.1.1.dist-info/WHEEL
webhooks_bridge-0.1.1.dist-info/RECORD
