Metadata-Version: 2.1
Name: webhooks-bridge
Version: 0.1.1
Summary: 
Home-page: https://github.com/SebastianLuebke/webhooks-bridge
Author: Sebastian Lübke
Author-email: github@luebke.io
Requires-Python: >=3.11,<4.0
Classifier: Programming Language :: Python :: 3
Classifier: Programming Language :: Python :: 3.11
Requires-Dist: Jinja2 (>=3.1.2,<4.0.0)
Requires-Dist: PyYAML (>=6.0,<7.0)
Requires-Dist: aiofiles (>=22.1.0,<23.0.0)
Requires-Dist: fastapi (>=0.89.1,<0.90.0)
Requires-Dist: httpx (>=0.23.3,<0.24.0)
Requires-Dist: uvicorn (>=0.20.0,<0.21.0)
Project-URL: Repository, https://github.com/SebastianLuebke/webhooks-bridge
